dajaxice/__init__.py
dajaxice/decorators.py
dajaxice/exceptions.py
dajaxice/finders.py
dajaxice/models.py
dajaxice/runtests.py
dajaxice/urls.py
dajaxice/utils.py
dajaxice/views.py
dajaxice/core/Dajaxice.py
dajaxice/core/__init__.py
dajaxice/templates/dajaxice/dajaxice.core.js
dajaxice/templates/dajaxice/dajaxice_function_loop.js
dajaxice/templates/dajaxice/dajaxice_module_loop.js
dajaxice/templatetags/__init__.py
dajaxice/templatetags/dajaxice_templatetags.py
django_dajaxice_ng-0.10.0.0.dist-info/AUTHORS
django_dajaxice_ng-0.10.0.0.dist-info/COPYING
django_dajaxice_ng-0.10.0.0.dist-info/METADATA
django_dajaxice_ng-0.10.0.0.dist-info/WHEEL
django_dajaxice_ng-0.10.0.0.dist-info/top_level.txt
django_dajaxice_ng-0.10.0.0.dist-info/RECORD
